README.md
setup.py
django_clickhouse_engine/__init__.py
django_clickhouse_engine/base.py
django_clickhouse_engine/client.py
django_clickhouse_engine/creation.py
django_clickhouse_engine/features.py
django_clickhouse_engine/introspection.py
django_clickhouse_engine/operations.py
django_clickhouse_engine.egg-info/PKG-INFO
django_clickhouse_engine.egg-info/SOURCES.txt
django_clickhouse_engine.egg-info/dependency_links.txt
django_clickhouse_engine.egg-info/requires.txt
django_clickhouse_engine.egg-info/top_level.txt